Lab/CA111-2_lab1/all_codes/ALU_Control.v
module ALU_Control(
    ALUOp_i,
    func3_i,
    func7_i,
    ALUCtr_o
);

input [1:0] ALUOp_i;
input [2:0] func3_i;
input [6:0] func7_i;
output [2:0] ALUCtr_o;

// define ALUCtr:
// and : 0000
// xor : 0001
// sll : 010
// add : 011
// sub : 100
// mul : 101
// addi : 011
// srai : 111


assign ALUCtr_o = (ALUOp_i == 2'b01 && func3_i == 3'b111) ? 3'b000 : //and 
                  (ALUOp_i == 2'b01 && func3_i == 3'b100) ? 3'b001 : //xor
                  (ALUOp_i == 2'b01 && func3_i == 3'b001) ? 3'b010 : //sll
                  (ALUOp_i == 2'b01 && func3_i == 3'b000 && func7_i == 7'b0000000) ? 3'b011 : //add
                  (ALUOp_i == 2'b01 && func3_i == 3'b000 && func7_i == 7'b0100000) ? 3'b100 : //sub
                  (ALUOp_i == 2'b01 && func3_i == 3'b000 && func7_i == 7'b0000001) ? 3'b101 : //mul
                  (ALUOp_i == 2'b00 && func3_i == 3'b000) ? 3'b011 : 3'b111; //addi & srai

endmodule

Lab/CA111-2_lab1/all_codes/ALU.v
module ALU(
    ALUCtr_i, 
    RS1data_i, 
    RS2data_i, 
    Zero_o, 
    RDdata_o
);

input [2:0] ALUCtr_i;
input signed [31:0] RS1data_i;
input [31:0] RS2data_i;
output Zero_o;
output [31:0] RDdata_o;

// case and if-else must be in an always block

assign RDdata_o = (ALUCtr_i == 3'b000) ? (RS1data_i & RS2data_i) : // and
                  (ALUCtr_i == 3'b001) ? (RS1data_i ^ RS2data_i) : // xor
                  (ALUCtr_i == 3'b010) ? (RS1data_i << RS2data_i) : // sll
                  (ALUCtr_i == 3'b011) ? (RS1data_i + RS2data_i) : // add
                  (ALUCtr_i == 3'b100) ? (RS1data_i - RS2data_i) : // sub
                  (ALUCtr_i == 3'b101) ? (RS1data_i * RS2data_i) : (RS1data_i >>> RS2data_i[4:0]); // mul : ALUCtr_i == 3'b111 (Srai)
                  //srai: https://nandland.com/shift-operator/

endmodule

Lab/CA111-2_lab1/all_codes/Sign_Extend.v
module Sign_Extend(
    imm_i,
    extendimm_o
);

input [11:0] imm_i;
output [31:0] extendimm_o;

assign extendimm_o = { {20{imm_i[11]}}, imm_i};

endmodule

Lab/CA111-2_lab1/all_codes/MUX_ALUSrc.v
module MUX32(
    ALUSrc_i, 
    RS2data_i,
    imm_i, 
    RS2data_o
);

input ALUSrc_i;
input [31:0] RS2data_i;
input [31:0] imm_i;
output [31:0] RS2data_o;

assign RS2data_o = (ALUSrc_i) ? imm_i : RS2data_i;

endmodule

Lab/CA111-2_lab1/all_codes/Add_PC.v
module Adder(
    pc_base_i,
    pc_offset_i,
    pc_o
);

input [31:0] pc_base_i;
input [31:0] pc_offset_i;
output [31:0] pc_o;

assign pc_o = pc_base_i + pc_offset_i;

endmodule

Lab/CA111-2_lab1/all_codes/Control.v
module Control(
    opcode_i, 
    ALUOp_o, 
    ALUSrc_o,
    RegWrite_o, 
);

input [6:0] opcode_i;
output [1:0] ALUOp_o;
output ALUSrc_o;
output RegWrite_o;

assign RegWrite_o = 1;

assign ALUSrc_o = (opcode_i == 7'b0110011 ) ? 0 : 1;
assign ALUOp_o = (opcode_i == 7'b0110011) ? 2'b01 : 2'b00;

endmodule

Lab/CA111-2_lab1/all_codes/Registers.v
module Registers
(
    clk_i,
    rst_i,
    RS1addr_i,
    RS2addr_i,
    RDaddr_i, 
    RDdata_i,
    RegWrite_i, 
    RS1data_o, 
    RS2data_o 
);

// Ports
input               rst_i;
input               clk_i;
input   [4:0]       RS1addr_i;
input   [4:0]       RS2addr_i;
input   [4:0]       RDaddr_i;
input   [31:0]      RDdata_i;
input               RegWrite_i;
output  [31:0]      RS1data_o; 
output  [31:0]      RS2data_o;
integer i;

// Register File
reg signed [31:0]      register        [0:31];

// Read Data      
assign  RS1data_o = register[RS1addr_i];
assign  RS2data_o = register[RS2addr_i];

// Write Data   
always@(posedge clk_i or negedge rst_i) begin
    if (~rst_i) begin
        for (i=0; i<32; i++) begin
            register[i] <= 32'b0;
        end
    end
    else if(RegWrite_i && RDaddr_i != 5'b0) begin
        register[RDaddr_i] <= RDdata_i;
    end
end
   
endmodule

Lab/CA111-2_lab1/all_codes/Instruction_Memory.v
module Instruction_Memory
(
    addr_i, 
    instr_o
);

// Interface
input   [31:0]      addr_i;
output  [31:0]      instr_o;

// Instruction memory
reg [31:0]     memory  [0:255];

assign  instr_o = memory[addr_i>>2];  // Shift 2 bits because each instruction is four-byte

endmodule

Lab/CA111-2_lab1/all_codes/PC.v
module PC
(
    clk_i,
    rst_i,
    pc_i,
    pc_o
);

// Ports
input               clk_i;
input               rst_i;
input   [31:0]      pc_i;
output  [31:0]      pc_o;

// Wires & Registers
reg     [31:0]      pc_o;

// When rst_i is 0, the reset is activated: reset to 0
// On the contrary, when rst_i is 1, the reset is deactivated: not reset, simply update
always@(posedge clk_i or negedge rst_i) begin /* 
If I simply define clk_i or rst_i, then the hardware will think it should do the block whenever clk_i change from 0 to 1 or 1 to 0
 */
    if(~rst_i) begin
        pc_o <= 32'b0;
    end
    else begin
        pc_o <= pc_i;
    end
end

endmodule

Lab/CA111-2_lab1/all_codes/CPU.v
module CPU
(
    clk_i, 
    rst_i,
);

// Ports
input               clk_i;
input               rst_i;

parameter adder_const = {{29{1'b0}}, {3'b100}};

// TODO: Noted that if I don't specify inputs in each module, it will follow the top module.
PC PC(
    .clk_i(clk_i),
    .rst_i(rst_i),
    .pc_i(Add_PC.pc_o)
);

Instruction_Memory Instruction_Memory(
    .addr_i(PC.pc_o)
);

Registers Registers(
    .clk_i(clk_i),
    .rst_i(rst_i),
    .RS1addr_i(Instruction_Memory.instr_o[19:15]),
    .RS2addr_i(Instruction_Memory.instr_o[24:20]),
    .RDaddr_i(Instruction_Memory.instr_o[11:7]), 
    .RDdata_i(ALU.RDdata_o),
    .RegWrite_i(Control.RegWrite_o) 
);

//Hints

Control Control(
    .opcode_i(Instruction_Memory.instr_o[6:0])
);

Adder Add_PC(
    .pc_base_i(PC.pc_o),
    .pc_offset_i(adder_const),
    .pc_o(PC.pc_i)
);

MUX32 MUX_ALUSrc(
    .ALUSrc_i(Control.ALUSrc_o), 
    .RS2data_i(Registers.RS2data_o),
    .imm_i(Sign_Extend.extendimm_o)
);

Sign_Extend Sign_Extend(
    .imm_i(Instruction_Memory.instr_o[31:20])
);
  
ALU ALU(
    .ALUCtr_i(ALU_Control.ALUCtr_o), 
    .RS1data_i(Registers.RS1data_o), 
    .RS2data_i(MUX_ALUSrc.RS2data_o)
);

ALU_Control ALU_Control(
    .ALUOp_i(Control.ALUOp_o),
    .func3_i(Instruction_Memory.instr_o[14:12]),
    .func7_i(Instruction_Memory.instr_o[31:25])
);

endmodule

Lab/CA111-2_lab1/all_codes/testbench.v
`define CYCLE_TIME 50            

module TestBench;

reg                Clk;
reg                Reset;
integer            i, outfile, counter;

always #(`CYCLE_TIME/2) Clk = ~Clk;    

CPU CPU(
    .clk_i  (Clk),
    .rst_i  (Reset)
);
  
initial begin

    $dumpfile("CPU.vcd");
    $dumpvars;

    counter = 0;
    
    // initialize instruction memory
    for(i=0; i<256; i=i+1) begin
        CPU.Instruction_Memory.memory[i] = 32'b0;
    end
    
    // Load instructions into instruction memory
    $readmemb("instruction.txt", CPU.Instruction_Memory.memory);
    
    // Open output file
    outfile = $fopen("output.txt") | 1;
    
    Clk = 0;
    Reset = 1;

    #(`CYCLE_TIME/8) 
    Reset = 0;

    #(`CYCLE_TIME/8) 
    Reset = 1;
end
  
always@(posedge Clk) begin
    if(counter == 30)    // stop after 30 cycles
        $finish;
        
    // print PC
    $fdisplay(outfile, "PC = %d", CPU.PC.pc_o);
    
    // print Registers
    $fdisplay(outfile, "Registers");
    $fdisplay(outfile, "x0     = %d, x8(s0)  = %d, x16(a6) = %d, x24(s8)  = %d", CPU.Registers.register[0], CPU.Registers.register[8] , CPU.Registers.register[16], CPU.Registers.register[24]);
    $fdisplay(outfile, "x1(ra) = %d, x9(s1)  = %d, x17(a7) = %d, x25(s9)  = %d", CPU.Registers.register[1], CPU.Registers.register[9] , CPU.Registers.register[17], CPU.Registers.register[25]);
    $fdisplay(outfile, "x2(sp) = %d, x10(a0) = %d, x18(s2) = %d, x26(s10) = %d", CPU.Registers.register[2], CPU.Registers.register[10], CPU.Registers.register[18], CPU.Registers.register[26]);
    $fdisplay(outfile, "x3(gp) = %d, x11(a1) = %d, x19(s3) = %d, x27(s11) = %d", CPU.Registers.register[3], CPU.Registers.register[11], CPU.Registers.register[19], CPU.Registers.register[27]);
    $fdisplay(outfile, "x4(tp) = %d, x12(a2) = %d, x20(s4) = %d, x28(t3)  = %d", CPU.Registers.register[4], CPU.Registers.register[12], CPU.Registers.register[20], CPU.Registers.register[28]);
    $fdisplay(outfile, "x5(t0) = %d, x13(a3) = %d, x21(s5) = %d, x29(t4)  = %d", CPU.Registers.register[5], CPU.Registers.register[13], CPU.Registers.register[21], CPU.Registers.register[29]);
    $fdisplay(outfile, "x6(t1) = %d, x14(a4) = %d, x22(s6) = %d, x30(t5)  = %d", CPU.Registers.register[6], CPU.Registers.register[14], CPU.Registers.register[22], CPU.Registers.register[30]);
    $fdisplay(outfile, "x7(t2) = %d, x15(a5) = %d, x23(s7) = %d, x31(t6)  = %d", CPU.Registers.register[7], CPU.Registers.register[15], CPU.Registers.register[23], CPU.Registers.register[31]);
    
    $fdisplay(outfile, "\n");
    
    counter = counter + 1;
end

  
endmodule

Lab/CA111-2_lab1/all_codes/CPU.vcd
$date
	Thu May 25 15:08:20 2023
$end
$version
	Icarus Verilog
$end
$timescale
	1s
$end
$scope module TestBench $end
$var reg 1 ! Clk $end
$var reg 1 " Reset $end
$var integer 32 # counter [31:0] $end
$var integer 32 $ i [31:0] $end
$var integer 32 % outfile [31:0] $end
$scope module CPU $end
$var wire 1 ! clk_i $end
$var wire 1 " rst_i $end
$scope module ALU $end
$var wire 1 & Zero_o $end
$var wire 32 ' RS2data_i [31:0] $end
$var wire 32 ( RS1data_i [31:0] $end
$var wire 32 ) RDdata_o [31:0] $end
$var wire 3 * ALUCtr_i [2:0] $end
$upscope $end
$scope module ALU_Control $end
$var wire 7 + func7_i [6:0] $end
$var wire 3 , func3_i [2:0] $end
$var wire 2 - ALUOp_i [1:0] $end
$var wire 3 . ALUCtr_o [2:0] $end
$upscope $end
$scope module Add_PC $end
$var wire 32 / pc_offset_i [31:0] $end
$var wire 32 0 pc_o [31:0] $end
$var wire 32 1 pc_base_i [31:0] $end
$upscope $end
$scope module Control $end
$var wire 1 2 RegWrite_o $end
$var wire 7 3 opcode_i [6:0] $end
$var wire 1 4 ALUSrc_o $end
$var wire 2 5 ALUOp_o [1:0] $end
$upscope $end
$scope module Instruction_Memory $end
$var wire 32 6 instr_o [31:0] $end
$var wire 32 7 addr_i [31:0] $end
$upscope $end
$scope module MUX_ALUSrc $end
$var wire 1 4 ALUSrc_i $end
$var wire 32 8 imm_i [31:0] $end
$var wire 32 9 RS2data_o [31:0] $end
$var wire 32 : RS2data_i [31:0] $end
$upscope $end
$scope module PC $end
$var wire 1 ! clk_i $end
$var wire 32 ; pc_i [31:0] $end
$var wire 1 " rst_i $end
$var reg 32 < pc_o [31:0] $end
$upscope $end
$scope module Registers $end
$var wire 5 = RDaddr_i [4:0] $end
$var wire 32 > RDdata_i [31:0] $end
$var wire 5 ? RS1addr_i [4:0] $end
$var wire 32 @ RS1data_o [31:0] $end
$var wire 5 A RS2addr_i [4:0] $end
$var wire 32 B RS2data_o [31:0] $end
$var wire 1 2 RegWrite_i $end
$var wire 1 ! clk_i $end
$var wire 1 " rst_i $end
$var integer 32 C i [31:0] $end
$upscope $end
$scope module Sign_Extend $end
$var wire 12 D imm_i [11:0] $end
$var wire 32 E extendimm_o [31:0] $end
$upscope $end
$upscope $end
$upscope $end
$enddefinitions $end
#0
$dumpvars
bx E
bx D
bx C
bx B
bx A
bx @
bx ?
bx >
bx =
bx <
bx ;
bx :
bx 9
bx 8
bx 7
bx 6
b0x 5
x4
bx 3
12
bx 1
bx 0
b100 /
bx .
b0x -
bx ,
bx +
bx *
bx )
bx (
bx '
z&
b11 %
b100000000 $
b0 #
1"
0!
$end
#6
b1010 )
b1010 >
b11 *
b11 .
14
b0 -
b0 5
b1010 '
b1010 9
b0 (
b0 @
b0 ?
b0 :
b0 B
b1010 A
b101 =
b10011 3
b1010 8
b1010 E
b1010 D
b0 ,
b0 +
b101000000000001010010011 6
b100 0
b100 ;
b0 1
b0 7
b0 <
b100000 C
0"
#12
1"
#25
b1101 )
b1101 >
b1101 '
b1101 9
b1101 A
b110 =
b1101 8
b1101 E
b1101 D
b110100000000001100010011 6
b1000 0
b1000 ;
b100 1
b100 7
b100 <
b1 #
1!
#50
0!
#75
b101 *
b101 .
b10000010 )
b10000010 >
04
b1 -
b1 5
b1101 '
b1101 9
b1010 (
b1010 @
b101 ?
b1101 :
b1101 B
b110 A
b111 =
b110011 3
b100110 8
b100110 E
b100110 D
b1 +
b10011000101000001110110011 6
b1100 0
b1100 ;
b1000 1
b1000 7
b1000 <
b10 #
1!
#100
0!
#125
b10101001 )
b10101001 >
b1101 (
b1101 @
b110 ?
b11100 =
b10011000110000111000110011 6
b10000 0
b10000 ;
b1100 1
b1100 7
b1100 <
b11 #
1!
#150
0!
#175
b1100 )
b1100 >
b11 *
b11 .
14
b11111111111111111111111111111111 '
b11111111111111111111111111111111 9
b0 -
b0 5
b0 :
b0 B
b11111 A
b110 =
b10011 3
b11111111111111111111111111111111 8
b11111111111111111111111111111111 E
b111111111111 D
b1111111 +
b11111111111100110000001100010011 6
b10100 0
b10100 ;
b10000 1
b10000 7
b10000 <
b100 #
1!
#200
0!
#225
b11111 )
b11111 >
b11111 '
b11111 9
b0 ?
b11110 =
b11111 8
b11111 E
b11111 D
b0 +
b1111100000000111100010011 6
b0 (
b0 @
b11000 0
b11000 ;
b10100 1
b10100 7
b10100 <
b101 #
1!
#250
0!
#275
b0 )
b0 >
b0 *
b0 .
04
b1 -
b1 5
b10000010 '
b10000010 9
b1100 (
b1100 @
b110 ?
b10000010 :
b10000010 B
b111 A
b11100 =
b110011 3
b111 8
b111 E
b111 D
b111 ,
b11100110111111000110011 6
b11100 0
b11100 ;
b11000 1
b11000 7
b11000 <
b110 #
1!
#300
0!
#325
b10000010 )
b10000010 >
b1 *
b1 .
b0 (
b0 @
b11100 ?
b11101 =
b100 ,
b11111100100111010110011 6
b100000 0
b100000 ;
b11100 1
b11100 7
b11100 <
b111 #
1!
#350
0!
#375
b0 )
b0 >
b0 '
b0 9
b1010 ?
b0 :
b0 B
b1101 A
b1110 =
b1101 8
b1101 E
b1101 D
b110101010100011100110011 6
b100100 0
b100100 ;
b100000 1
b100000 7
b100000 <
b1000 #
1!
#400
0!
#425
b11111111111111111111111101111110 )
b11111111111111111111111101111110 >
b100 *
b100 .
b10000010 '
b10000010 9
b11100 ?
b10000010 :
b10000010 B
b111 A
b101 =
b10000000111 8
b10000000111 E
b10000000111 D
b0 ,
b100000 +
b1000000011111100000001010110011 6
b101000 0
b101000 ;
b100100 1
b100100 7
b100100 <
b1001 #
1!
#450
0!
#475
b11111111111111111111111111111000 )
b11111111111111111111111111111000 >
b11 *
b11 .
14
b11111111111111111111111111111000 '
b11111111111111111111111111111000 9
b0 -
b0 5
b11111 ?
b0 :
b0 B
b11000 A
b11111 =
b10011 3
b11111111111111111111111111111000 8
b11111111111111111111111111111000 E
b111111111000 D
b1111111 +
b11111111100011111000111110010011 6
b101100 0
b101100 ;
b101000 1
b101000 7
b101000 <
b1010 #
1!
#500
0!
#525
b11111111111111111111111111110000 )
b11111111111111111111111111110000 >
b11111111111111111111111111111000 (
b11111111111111111111111111111000 @
b110000 0
b110000 ;
b101100 1
b101100 7
b101100 <
b1011 #
1!
#550
0!
#575
b11111111111111111111111111101000 )
b11111111111111111111111111101000 >
b110100 0
b110100 ;
b110000 1
b110000 7
b110000 <
b11111111111111111111111111110000 (
b11111111111111111111111111110000 @
b1100 #
1!
#600
0!
#625
b111111 )
b111111 >
b111111 '
b111111 9
b0 ?
b11111111111111111111111111101000 :
b11111111111111111111111111101000 B
b11111 A
b111 =
b111111 8
b111111 E
b111111 D
b1 +
b11111100000000001110010011 6
b0 (
b0 @
b111000 0
b111000 ;
b110100 1
b110100 7
b110100 <
b1101 #
1!
#650
0!
#675
b111 *
b111 .
b1111 )
b1111 >
b10000000010 '
b10000000010 9
b111111 (
b111111 @
b111 ?
b0 :
b0 B
b10 A
b10000000010 8
b10000000010 E
b10000000010 D
b101 ,
b100000 +
b1000000001000111101001110010011 6
b111100 0
b111100 ;
b111000 1
b111000 7
b111000 <
b1110 #
1!
#700
0!
#725
b11 )
b11 >
b1111 (
b1111 @
b1000000 0
b1000000 ;
b111100 1
b111100 7
b111100 <
b1111 #
1!
#750
0!
#775
b0 )
b0 >
b1000100 0
b1000100 ;
b1000000 1
b1000000 7
b1000000 <
b11 (
b11 @
b10000 #
1!
#800
0!
#825
b110 )
b110 >
b10000000001 '
b10000000001 9
b110 ?
b1 A
b110 =
b10000000001 8
b10000000001 E
b10000000001 D
b1000000000100110101001100010011 6
b1100 (
b1100 @
b1001000 0
b1001000 ;
b1000100 1
b1000100 7
b1000100 <
b10001 #
1!
#850
0!
#875
b11 )
b11 >
b1001100 0
b1001100 ;
b1001000 1
b1001000 7
b1001000 <
b110 (
b110 @
b10010 #
1!
#900
0!
#925
b1 )
b1 >
b11 (
b11 @
b1010000 0
b1010000 ;
b1001100 1
b1001100 7
b1001100 <
b10011 #
1!
#950
0!
#975
b10 *
b10 .
b11111111111111111111111111010000 )
b11111111111111111111111111010000 >
04
b1 -
b1 5
b1 '
b1 9
b11111 ?
b1 :
b1 B
b110 A
b11111 =
b110011 3
b110 8
b110 E
b110 D
b1 ,
b0 +
b11011111001111110110011 6
b1010100 0
b1010100 ;
b1010000 1
b1010000 7
b1010000 <
b11111111111111111111111111101000 (
b11111111111111111111111111101000 @
b10100 #
1!
#1000
0!
#1025
b11111111111111111111111110100000 )
b11111111111111111111111110100000 >
b11111111111111111111111111010000 (
b11111111111111111111111111010000 @
b1011000 0
b1011000 ;
b1010100 1
b1010100 7
b1010100 <
b10101 #
1!
#1050
0!
#1075
b11 *
b11 .
14
b0 '
b0 9
b0 -
b0 5
b0 )
b0 >
b0 ?
b0 :
b0 B
b0 A
b0 =
b0 3
b0 8
b0 E
b0 D
b0 ,
b0 6
b1011100 0
b1011100 ;
b1011000 1
b1011000 7
b1011000 <
b0 (
b0 @
b10110 #
1!
#1100
0!
#1125
b1100000 0
b1100000 ;
b1011100 1
b1011100 7
b1011100 <
b10111 #
1!
#1150
0!
#1175
b1100100 0
b1100100 ;
b1100000 1
b1100000 7
b1100000 <
b11000 #
1!
#1200
0!
#1225
b1101000 0
b1101000 ;
b1100100 1
b1100100 7
b1100100 <
b11001 #
1!
#1250
0!
#1275
b1101100 0
b1101100 ;
b1101000 1
b1101000 7
b1101000 <
b11010 #
1!
#1300
0!
#1325
b1110000 0
b1110000 ;
b1101100 1
b1101100 7
b1101100 <
b11011 #
1!
#1350
0!
#1375
b1110100 0
b1110100 ;
b1110000 1
b1110000 7
b1110000 <
b11100 #
1!
#1400
0!
#1425
b1111000 0
b1111000 ;
b1110100 1
b1110100 7
b1110100 <
b11101 #
1!
#1450
0!
#1475
b1111100 0
b1111100 ;
b1111000 1
b1111000 7
b1111000 <
b11110 #
1!
#1500
0!
#1525
b10000000 0
b10000000 ;
b1111100 1
b1111100 7
b1111100 <
1!
